pyilluminate/__init__.py
pyilluminate/_static_version.py
pyilluminate/_version.py
pyilluminate/conftest.py
pyilluminate/fake_illuminate.py
pyilluminate/illuminate.py
pyilluminate/tests/__init__.py
pyilluminate/tests/test_basic.py
pyilluminate/tests/test_fake_illuminate.py
pyilluminate/tests/test_filelock.py
pyilluminate/tests/test_find_max_brightness.py
pyilluminate/tests/test_led_color.py
pyilluminate/tests/test_led_commands.py
pyilluminate/tests/test_led_state.py
pyilluminate/tests/test_open.py
pyilluminate-0.7.0.dist-info/LICENSE
pyilluminate-0.7.0.dist-info/METADATA
pyilluminate-0.7.0.dist-info/WHEEL
pyilluminate-0.7.0.dist-info/top_level.txt
pyilluminate-0.7.0.dist-info/RECORD
