Metadata-Version: 2.1
Name: pyilluminate
Version: 0.7.0
Home-page: https://github.com/ramonaoptics/pyilluminate
Author: Ramona Optics, Inc.
Author-email: info@ramonaoptics.com
License: BSD
Requires-Python: >=3.7
License-File: LICENSE
Requires-Dist: pyserial
Requires-Dist: multiuserfilelock
Requires-Dist: xarray
